libinsitu/__init__.py
libinsitu/_version.py
libinsitu/catalog.py
libinsitu/cdl.py
libinsitu/common.py
libinsitu/log.py
libinsitu/qc_utils.py
libinsitu/cli/__init__.py
libinsitu/cli/cat.py
libinsitu/cli/check.py
libinsitu/cli/diff.py
libinsitu/cli/dump.py
libinsitu/cli/enrich_csv.py
libinsitu/cli/index.py
libinsitu/cli/info.py
libinsitu/cli/ls.py
libinsitu/cli/qc.py
libinsitu/cli/sync.py
libinsitu/cli/transform.py
libinsitu/cli/update_meta.py
libinsitu/handlers/ABOM.py
libinsitu/handlers/BSRN.py
libinsitu/handlers/ESMAP.py
libinsitu/handlers/GenericCSVHandler.py
libinsitu/handlers/GenericHandler.py
libinsitu/handlers/GenericMappingHandler.py
libinsitu/handlers/IEA_PVPS.py
libinsitu/handlers/ISE_PVLive.py
libinsitu/handlers/METEO_FRANCE.py
libinsitu/handlers/NREL_MIDC.py
libinsitu/handlers/NetCDFHandler.py
libinsitu/handlers/RAD.py
libinsitu/handlers/SAURAN.py
libinsitu/handlers/SKYNET.py
libinsitu/handlers/SOLRAD.py
libinsitu/handlers/SURFRAD.py
libinsitu/handlers/UniOregon_readdata.py
libinsitu/handlers/__init__.py
libinsitu/handlers/base_handler.py
libinsitu/handlers/enerMENA.py
libinsitu/qc/__init__.py
libinsitu/qc/app.py
libinsitu/qc/base_graphs.py
libinsitu/qc/graphs.py
libinsitu/qc/layout.py
libinsitu/qc/qc_utils.py
libinsitu/qc/graphs/__init__.py
libinsitu/qc/graphs/base.py
libinsitu/qc/graphs/main_layout.py
libinsitu/qc/matplot/__init__.py
libinsitu/qc/matplot/graphs.py
libinsitu/qc/plotly/__init__.py
libinsitu/res/IEA_PVPS.cdl
libinsitu/res/__init__.py
libinsitu/res/base.cdl
libinsitu/res/index.cdl
libinsitu/res/networks.csv
libinsitu/res/qc-tests.csv
libinsitu/res/station-info/ABOM.csv
libinsitu/res/station-info/BSRN.csv
libinsitu/res/station-info/ESMAP.csv
libinsitu/res/station-info/IEAPVPST16.csv
libinsitu/res/station-info/IEA_PVPS.csv
libinsitu/res/station-info/ISE_PVLive.csv
libinsitu/res/station-info/METEO_FRANCE.csv
libinsitu/res/station-info/NREL_MIDC.csv
libinsitu/res/station-info/SAURAN.csv
libinsitu/res/station-info/SKYNET.csv
libinsitu/res/station-info/SOLRAD.csv
libinsitu/res/station-info/SURFRAD.csv
libinsitu/res/station-info/__init__.py
libinsitu/res/station-info/enerMENA.csv
libinsitu/test/end_to_end.py
libinsitu/test/out.csv
libinsitu/test/unit_tests.py
libinsitu/test/utils.py
libinsitu/test/data/config/CARNASRDA/mapping.json
libinsitu/test/data/config/CARNASRDA/stations.csv
libinsitu/test/data/expected/ABOM.csv
libinsitu/test/data/expected/BSRN-ILO-qc.png
libinsitu/test/data/expected/BSRN.csv
libinsitu/test/data/expected/CARNASRDA.csv
libinsitu-1.7.dist-info/licenses/LICENSE
libinsitu-1.7.dist-info/METADATA
libinsitu-1.7.dist-info/WHEEL
libinsitu-1.7.dist-info/entry_points.txt
libinsitu-1.7.dist-info/top_level.txt
libinsitu-1.7.dist-info/RECORD
