Metadata-Version: 2.4
Name: libinsitu
Version: 1.7
Summary: This library provides tools to transform solar irradiation data from various networks to uniform NetCDF files. It also provides tools to request and manipulate those NetCDF files
Home-page: http://libinsitu.org/
Author: OIE - Mines ParisTech
Author-email: raphael.jolivet@mines-paristech.fr
License: BSD
Keywords: in-situ,solar,pv,irradiation,NetCDF,FAIR,meta-data
Requires-Python: >=3.9, <3.13
License-File: LICENSE
Requires-Dist: numpy
Requires-Dist: jsonpickle~=2.1
Requires-Dist: netCDF4
Requires-Dist: openpyxl~=3.0
Requires-Dist: pandas
Requires-Dist: pvlib~=0.9
Requires-Dist: python_dateutil~=2.8
Requires-Dist: pytz~=2022.1
Requires-Dist: requests~=2.27
Requires-Dist: rich~=12.2
Requires-Dist: six~=1.16
Requires-Dist: Unidecode~=1.3
Requires-Dist: matplotlib~=3.5
Requires-Dist: xlrd~=2.0
Requires-Dist: python-dotenv
Requires-Dist: diskcache
Requires-Dist: appdirs
Requires-Dist: sg2
Requires-Dist: jmespath
Requires-Dist: StrEnum
Requires-Dist: timezonefinder
Requires-Dist: pyyaml
Requires-Dist: timedelta-isoformat
Requires-Dist: siphon
Requires-Dist: xarray
Dynamic: author
Dynamic: author-email
Dynamic: description
Dynamic: description-content-type
Dynamic: home-page
Dynamic: keywords
Dynamic: license
Dynamic: license-file
Dynamic: requires-dist
Dynamic: requires-python
Dynamic: summary
